.DS_Store
simplehand/__init__.py
simplehand/hand_structure.py
simplehand/simplehand.py
simplehand-0.1.2.dist-info/LICENSE
simplehand-0.1.2.dist-info/METADATA
simplehand-0.1.2.dist-info/WHEEL
simplehand-0.1.2.dist-info/top_level.txt
simplehand-0.1.2.dist-info/RECORD
