Metadata-Version: 2.1
Name: simplehand
Version: 0.1.2
Summary: A simple 3D hand visualizer
Home-page: https://github.com/jtcostello/simplehand
Author: Joey Costello
Author-email: your_email@example.com
Classifier: Programming Language :: Python :: 3
Classifier: License :: OSI Approved :: MIT License
Classifier: Operating System :: OS Independent
License-File: LICENSE
Requires-Dist: numpy
Requires-Dist: matplotlib
